{
  "url": "http://vocaro.wikidot.com/nonsugirl",
  "page": "논슈걸",
  "title": "ノンシュガール",
  "songLink": "",
  "composer": "tamaGO",
  "lyricist": "tamaGO",
  "singer": "모모네 모모",
  "lyrics": [
    "泣いてるのは痛いからじゃない",
    "나이테루노와 이타이카라자 나이",
    "울고 있는 건 아파서가 아니야",
    "あなたがいないからだ",
    "아나타가 이나이카라다",
    "당신이 없기 때문이야",
    "会いたいのは痛い体を",
    "아이타이노와 이타이 카라다오",
    "만나고 싶은 건 아픈 몸을",
    "あなたが呼ぶからだ",
    "아나타가 요부카라다",
    "당신이 불러서야",
    "耳を塞ぐの　音が逃げないように",
    "미미오 후사구노 오토가 니게나이 요오니",
    "귀를 막아, 소리가 달아나지 않도록",
    "夢も理想も音で見えないでしょ？",
    "유메모 리소오모 오토데 미에나이데쇼?",
    "꿈도 이상도 소리에 보이지 않잖아?",
    "いますぐ",
    "이마스구",
    "지금 당장"
  ]
}