{
  "pageUrl": "/neighborhood-zoo",
  "pageTitle": "근처의 동물원",
  "originalTitle": "界隈の動物園",
  "songInfo": [
    {
      "originalUrl": "https://www.youtube.com/watch?v=_oQ4wb0NbcQ",
      "composer": [
        "바바파파"
      ],
      "lyricist": [
        "바바파파"
      ],
      "singer": [
        "데포코"
      ]
    }
  ],
  "lyricsInfo": [
    {
      "lyrics": [
        "あのね僕の波動が",
        "아노네 보쿠노 하도오가",
        "있죠, 나의 파동이",
        "君をここへ呼びました",
        "키미오 코코에 요비마시타",
        "당신을 여기로 불렀습니다",
        "ここが新しい場所",
        "코코가 아타라시이 바쇼",
        "여기가 새로운 장소",
        "黒が笑いました",
        "쿠로가 와라이마시타",
        "흑막이 웃었습니다",
        "電波はどこへ行く",
        "덴파와 도코에 이쿠",
        "전파는 어디로 가나",
        "流れ着いた三角形",
        "나가레츠이타 산카쿠케이",
        "떠돌다 다다른 삼각형",
        "伝播したその先",
        "덴파시타 소노 사키",
        "전파되던 그 끝",
        "手を引いた手を引いた",
        "테오 히이타 테오 히이타",
        "손을 끌었어, 손을 끌었어",
        "あのね君の波長は",
        "아노네 키미노 하초오와",
        "있죠, 당신의 파동은",
        "誰も見つけられなくて",
        "다레모 미츠케라레나쿠테",
        "아무도 찾아내지 못해서",
        "一人きりの迷路で",
        "히토리키리노 메이로데",
        "혼자뿐인 미로에서",
        "僕を呼ぶ",
        "보쿠오 요부",
        "나를 불러",
        "あのね僕の波動が",
        "아노네 보쿠노 하도오가",
        "있죠, 나의 파동이",
        "君をここへ呼びました",
        "키미오 코코에 요비마시타",
        "당신을 여기로 불렀습니다",
        "ここが新しい場所",
        "코코가 아타라시이 바쇼",
        "여기가 새로운 장소",
        "黒が笑いました",
        "쿠로가 와라이마시타",
        "흑막이 웃었습니다"
      ]
    }
  ]
}